download_canadian_stations.py
download_canadian_stations-1.0.dist-info/entry_points.txt
download_canadian_stations-1.0.dist-info/LICENSE
download_canadian_stations-1.0.dist-info/WHEEL
download_canadian_stations-1.0.dist-info/METADATA
download_canadian_stations-1.0.dist-info/RECORD
