Metadata-Version: 2.1
Name: download_canadian_stations
Version: 1.0
Summary: Download data about all active Environment Canada weather stations
Home-page: https://github.com/timdaman/download_stations
License: UNKNOWN
Author: Tim Laurence
Author-email: timdaman@gmail.com
Classifier: License :: OSI Approved :: Apache Software License
Requires-Dist: requests
Requires-Dist: beautifulsoup4
